pyecsca/ec/__init__.py
pyecsca/ec/configuration.py
pyecsca/ec/context.py
pyecsca/ec/coordinates.py
pyecsca/ec/countermeasures.py
pyecsca/ec/curve.py
pyecsca/ec/divpoly.py
pyecsca/ec/error.py
pyecsca/ec/key_agreement.py
pyecsca/ec/key_generation.py
pyecsca/ec/model.py
pyecsca/ec/op.py
pyecsca/ec/params.py
pyecsca/ec/point.py
pyecsca/ec/scalar.py
pyecsca/ec/signature.py
pyecsca/ec/transformations.py
pyecsca/ec/data/formulas/add-bc-r1rv76-jac
pyecsca/ec/data/formulas/add-bc-r1rv76-jac.op3
pyecsca/ec/data/formulas/add-bc-r1rv76-mod
pyecsca/ec/data/formulas/add-bc-r1rv76-mod.op3
pyecsca/ec/data/formulas/add-bearssl-v06
pyecsca/ec/data/formulas/add-bearssl-v06.op3
pyecsca/ec/data/formulas/add-boringssl-p224
pyecsca/ec/data/formulas/add-boringssl-p224.op3
pyecsca/ec/data/formulas/add-gecc-322
pyecsca/ec/data/formulas/add-gecc-322.op3
pyecsca/ec/data/formulas/add-libgcrypt-v1102
pyecsca/ec/data/formulas/add-libgcrypt-v1102.op3
pyecsca/ec/data/formulas/add-libressl-v382
pyecsca/ec/data/formulas/add-libressl-v382.op3
pyecsca/ec/data/formulas/add-openssl-z256
pyecsca/ec/data/formulas/add-openssl-z256.op3
pyecsca/ec/data/formulas/add-openssl-z256a
pyecsca/ec/data/formulas/add-openssl-z256a.op3
pyecsca/ec/data/formulas/add-sunec-v21
pyecsca/ec/data/formulas/add-sunec-v21-ed25519
pyecsca/ec/data/formulas/add-sunec-v21-ed25519.op3
pyecsca/ec/data/formulas/add-sunec-v21.op3
pyecsca/ec/data/formulas/dbl-bc-r1rv76-jac
pyecsca/ec/data/formulas/dbl-bc-r1rv76-jac.op3
pyecsca/ec/data/formulas/dbl-bc-r1rv76-mod
pyecsca/ec/data/formulas/dbl-bc-r1rv76-mod.op3
pyecsca/ec/data/formulas/dbl-bc-r1rv76-x25519
pyecsca/ec/data/formulas/dbl-bc-r1rv76-x25519.op3
pyecsca/ec/data/formulas/dbl-bearssl-v06
pyecsca/ec/data/formulas/dbl-bearssl-v06.op3
pyecsca/ec/data/formulas/dbl-boringssl-p224
pyecsca/ec/data/formulas/dbl-boringssl-p224.op3
pyecsca/ec/data/formulas/dbl-gecc-321
pyecsca/ec/data/formulas/dbl-gecc-321.op3
pyecsca/ec/data/formulas/dbl-hacl-x25519
pyecsca-0.4.0.dist-info/licenses/LICENSE
pyecsca-0.4.0.dist-info/METADATA
pyecsca-0.4.0.dist-info/WHEEL
pyecsca-0.4.0.dist-info/top_level.txt
pyecsca-0.4.0.dist-info/RECORD
