Metadata-Version: 2.4
Name: pyecsca
Version: 0.4.0
Summary: Python Elliptic Curve cryptography Side Channel Analysis toolkit.
Author: Jan Jancar, Tomas Jusko, Andrej Batora, Vojtech Suchanek
Author-email: Jan Jancar <johny@neuromancer.sk>
Maintainer-email: Jan Jancar <johny@neuromancer.sk>
License: MIT
Project-URL: Homepage, https://pyecsca.org
Project-URL: Documentation, https://pyecsca.org
Project-URL: Bug Tracker, https://github.com/J08nY/pyecsca/issues
Project-URL: Repository, https://github.com/J08nY/pyecsca
Classifier: Development Status :: 4 - Beta
Classifier: License :: OSI Approved :: MIT License
Classifier: Topic :: Security
Classifier: Topic :: Security :: Cryptography
Classifier: Programming Language :: Python :: 3.9
Classifier: Programming Language :: Python :: 3.10
Classifier: Programming Language :: Python :: 3.11
Classifier: Programming Language :: Python :: 3.12
Classifier: Programming Language :: Python :: 3.13
Classifier: Intended Audience :: Developers
Classifier: Intended Audience :: Science/Research
Requires-Python: >=3.9
License-File: LICENSE
Requires-Dist: numpy
Requires-Dist: scipy
Requires-Dist: sympy!=1.14.0,>=1.7.1
Requires-Dist: pandas
Requires-Dist: atpublic
Requires-Dist: cython
Requires-Dist: fastdtw
Requires-Dist: asn1crypto
Requires-Dist: h5py
Requires-Dist: holoviews
Requires-Dist: bokeh
Requires-Dist: matplotlib
Requires-Dist: seaborn
Requires-Dist: datashader
Requires-Dist: dask[dataframe]
Requires-Dist: xarray
Requires-Dist: astunparse
Requires-Dist: numba
Requires-Dist: networkx
Requires-Dist: importlib-resources
Requires-Dist: anytree
Requires-Dist: loky
Provides-Extra: picoscope-sdk
Requires-Dist: picosdk; extra == "picoscope-sdk"
Provides-Extra: picoscope-alt
Requires-Dist: picoscope; extra == "picoscope-alt"
Provides-Extra: chipwhisperer
Requires-Dist: chipwhisperer; extra == "chipwhisperer"
Provides-Extra: smartcard
Requires-Dist: pyscard; extra == "smartcard"
Provides-Extra: leia
Requires-Dist: smartleia; extra == "leia"
Provides-Extra: gmp
Requires-Dist: gmpy2; extra == "gmp"
Provides-Extra: flint
Requires-Dist: python-flint>=0.5.0; extra == "flint"
Provides-Extra: pari
Requires-Dist: cysignals; extra == "pari"
Requires-Dist: cypari2; extra == "pari"
Provides-Extra: dev
Requires-Dist: mypy; extra == "dev"
Requires-Dist: flake8; extra == "dev"
Requires-Dist: interrogate; extra == "dev"
Requires-Dist: black; extra == "dev"
Requires-Dist: types-setuptools; extra == "dev"
Requires-Dist: pydocstyle; extra == "dev"
Provides-Extra: test
Requires-Dist: pytest>=7.0.0; extra == "test"
Requires-Dist: coverage; extra == "test"
Requires-Dist: pytest-cov; extra == "test"
Requires-Dist: pytest-sugar; extra == "test"
Requires-Dist: pytest-mock; extra == "test"
Requires-Dist: nbmake; extra == "test"
Requires-Dist: pyinstrument; extra == "test"
Provides-Extra: doc
Requires-Dist: sphinx; extra == "doc"
Requires-Dist: sphinx-autodoc-typehints; extra == "doc"
Requires-Dist: nbsphinx; extra == "doc"
Requires-Dist: sphinx-paramlinks; extra == "doc"
Requires-Dist: sphinx_design; extra == "doc"
Requires-Dist: sphinx-plausible; extra == "doc"
Requires-Dist: alabaster>=0.7.16; extra == "doc"
Dynamic: license-file
